atomdb/__init__.py
atomdb/base.py
atomdb/nosql.py
atomdb/py.typed
atomdb/sql.py
atom_db-0.8.2.dist-info/LICENSE
atom_db-0.8.2.dist-info/METADATA
atom_db-0.8.2.dist-info/WHEEL
atom_db-0.8.2.dist-info/top_level.txt
atom_db-0.8.2.dist-info/RECORD
