Metadata-Version: 2.1
Name: atom-db
Version: 0.8.2
Summary: Database abstraction layer for atom objects
Home-page: https://github.com/codelv/atom-db
Author: CodeLV
Author-email: frmdstryr@gmail.com
License: MIT
Requires: atom
Requires-Python: >=3.7
License-File: LICENSE
Requires-Dist: atom>=0.7.0
